tests/__init__.py
tests/__main__.py
tests/ner.py
tests/ner_chinese.py
tests/ner_chinese_embedding.py
tests/ner_glove.py
tests/ner_glove_charcnn.py
tests/segmentation_glove.py
tests/test_encoder_rnn.py
tests/test_grid.py
tests/test_model.py
tests/test_ner.py
tests/test_score_table.py
tests/test_simple.py
tests/test_simple_cn.py
tests/test_tagger.py
tests/test_utils.py
torch_tagger/__init__.py
torch_tagger/char_cnn.py
torch_tagger/char_rnn.py
torch_tagger/decoder_crf.py
torch_tagger/decoder_softmax.py
torch_tagger/encoder_rnn.py
torch_tagger/tagger.py
torch_tagger/tagger_dataset.py
torch_tagger/tagger_model.py
torch_tagger/torch_lm.py
torch_tagger/utils.py
torch_tagger/version.txt
torch_tagger/word_orders.json
torch_tagger-0.0.61.dist-info/DESCRIPTION.rst
torch_tagger-0.0.61.dist-info/METADATA
torch_tagger-0.0.61.dist-info/RECORD
torch_tagger-0.0.61.dist-info/WHEEL
torch_tagger-0.0.61.dist-info/metadata.json
torch_tagger-0.0.61.dist-info/top_level.txt
