Metadata-Version: 2.0
Name: torch-tagger
Version: 0.0.61
Summary: NLP tool
Home-page: https://github.com/infinity-future/torch-tagger
Author: infinityfuture
Author-email: infinityfuture@foxmail.com
License: Private
Keywords: pip,pytorch,NER,tagger
Platform: any
Requires-Dist: numpy
Requires-Dist: pypinyin
Requires-Dist: scikit-learn
Requires-Dist: scipy
Requires-Dist: torch
Requires-Dist: tqdm
